autolens/__init__.py
autolens/conf.py
autolens/exc.py
autolens/fixtures.py
autolens/mock.py
autolens/aggregator/__init__.py
autolens/aggregator/fit_imaging.py
autolens/aggregator/fit_interferometer.py
autolens/aggregator/subhalo.py
autolens/aggregator/subplot.py
autolens/aggregator/tracer.py
autolens/analysis/__init__.py
autolens/analysis/model_util.py
autolens/analysis/plotter_interface.py
autolens/analysis/positions.py
autolens/analysis/result.py
autolens/analysis/analysis/__init__.py
autolens/analysis/analysis/dataset.py
autolens/analysis/analysis/lens.py
autolens/config/general.yaml
autolens/config/non_linear.yaml
autolens/config/output.yaml
autolens/config/visualize/plots.yaml
autolens/imaging/__init__.py
autolens/imaging/fit_imaging.py
autolens/imaging/simulator.py
autolens/imaging/mock/__init__.py
autolens/imaging/mock/mock_fit_imaging.py
autolens/imaging/model/__init__.py
autolens/imaging/model/analysis.py
autolens/imaging/model/plotter_interface.py
autolens/imaging/model/result.py
autolens/imaging/model/visualizer.py
autolens/imaging/plot/__init__.py
autolens/imaging/plot/fit_imaging_plotters.py
autolens/interferometer/__init__.py
autolens/interferometer/fit_interferometer.py
autolens/interferometer/simulator.py
autolens/interferometer/model/__init__.py
autolens/interferometer/model/analysis.py
autolens/interferometer/model/plotter_interface.py
autolens/interferometer/model/result.py
autolens/interferometer/model/visualizer.py
autolens/interferometer/plot/__init__.py
autolens/interferometer/plot/fit_interferometer_plotters.py
autolens/lens/__init__.py
autolens/lens/sensitivity.py
autolens/lens/subhalo.py
autolens/lens/to_inversion.py
autolens/lens/tracer.py
autolens/lens/tracer_util.py
autolens/lens/mock/__init__.py
autolens/lens/mock/mock_to_inversion.py
autolens/lens/mock/mock_tracer.py
autolens/lens/plot/__init__.py
autolens/lens/plot/tracer_plotters.py
autolens/plot/__init__.py
autolens/plot/abstract_plotters.py
autolens/point/__init__.py
autolens-2026.1.21.3.dist-info/licenses/LICENSE
autolens-2026.1.21.3.dist-info/METADATA
autolens-2026.1.21.3.dist-info/WHEEL
autolens-2026.1.21.3.dist-info/top_level.txt
autolens-2026.1.21.3.dist-info/RECORD
