Metadata-Version: 2.4
Name: autolens
Version: 2026.1.21.3
Summary: Open-Source Strong Lensing
Author-email: James Nightingale <James.Nightingale@newcastle.ac.uk>, Richard Hayes <richard@rghsoftware.co.uk>
License: MIT
Project-URL: Homepage, https://github.com/Jammy2211/PyAutoLens
Keywords: cli
Classifier: Intended Audience :: Science/Research
Classifier: Topic :: Scientific/Engineering :: Physics
Classifier: Natural Language :: English
Classifier: Operating System :: OS Independent
Classifier: Programming Language :: Python :: 3.9
Classifier: Programming Language :: Python :: 3.10
Classifier: Programming Language :: Python :: 3.11
Classifier: Programming Language :: Python :: 3.12
Requires-Python: >=3.9
License-File: LICENSE
Requires-Dist: autogalaxy
Requires-Dist: nautilus-sampler==1.0.5
Provides-Extra: optional
Requires-Dist: numba; extra == "optional"
Requires-Dist: pynufft; extra == "optional"
Requires-Dist: ultranest==3.6.2; extra == "optional"
Requires-Dist: zeus-mcmc==2.5.4; extra == "optional"
Requires-Dist: getdist==1.4; extra == "optional"
Provides-Extra: docs
Requires-Dist: sphinx; extra == "docs"
Requires-Dist: furo; extra == "docs"
Requires-Dist: myst-parser; extra == "docs"
Requires-Dist: sphinx_copybutton; extra == "docs"
Requires-Dist: sphinx_design; extra == "docs"
Requires-Dist: sphinx_inline_tabs; extra == "docs"
Requires-Dist: sphinx_autodoc_typehints; extra == "docs"
Provides-Extra: test
Requires-Dist: pytest; extra == "test"
Provides-Extra: dev
Requires-Dist: pytest; extra == "dev"
Requires-Dist: black; extra == "dev"
Dynamic: license-file
